BCSFE_FIX/__init__.py
BCSFE_FIX/__main__.py
BCSFE_FIX/adb_handler.py
BCSFE_FIX/config_manager.py
BCSFE_FIX/csv_handler.py
BCSFE_FIX/feature_handler.py
BCSFE_FIX/game_data_getter.py
BCSFE_FIX/helper.py
BCSFE_FIX/item.py
BCSFE_FIX/locale_handler.py
BCSFE_FIX/managed_item.py
BCSFE_FIX/parse_save.py
BCSFE_FIX/patcher.py
BCSFE_FIX/py.typed
BCSFE_FIX/root_handler.py
BCSFE_FIX/serialise_save.py
BCSFE_FIX/server_handler.py
BCSFE_FIX/updater.py
BCSFE_FIX/user_info.py
BCSFE_FIX/user_input_handler.py
BCSFE_FIX/edits/__init__.py
BCSFE_FIX/edits/basic/__init__.py
BCSFE_FIX/edits/basic/basic_items.py
BCSFE_FIX/edits/basic/catfruit.py
BCSFE_FIX/edits/basic/catseyes.py
BCSFE_FIX/edits/basic/ototo_base_mats.py
BCSFE_FIX/edits/basic/talent_orbs.py
BCSFE_FIX/edits/basic/talent_orbs_new.py
BCSFE_FIX/edits/cats/__init__.py
BCSFE_FIX/edits/cats/cat_helper.py
BCSFE_FIX/edits/cats/cat_id_selector.py
BCSFE_FIX/edits/cats/chara_drop.py
BCSFE_FIX/edits/cats/clear_cat_guide.py
BCSFE_FIX/edits/cats/evolve_cats.py
BCSFE_FIX/edits/cats/get_remove_cats.py
BCSFE_FIX/edits/cats/talents.py
BCSFE_FIX/edits/cats/upgrade_blue.py
BCSFE_FIX/edits/cats/upgrade_cats.py
BCSFE_FIX/edits/gamototo/__init__.py
BCSFE_FIX/edits/gamototo/fix_gamatoto.py
BCSFE_FIX/edits/gamototo/gamatoto_xp.py
BCSFE_FIX/edits/gamototo/helpers.py
BCSFE_FIX/edits/gamototo/ototo_cat_cannon.py
BCSFE_FIX/edits/levels/__init__.py
BCSFE_FIX/edits/levels/aku.py
BCSFE_FIX/edits/levels/allow_filibuster_clearing.py
BCSFE_FIX/edits/levels/behemoth_culling.py
BCSFE_FIX/edits/levels/clear_tutorial.py
BCSFE_FIX/edits/levels/enigma_stages.py
BCSFE_FIX/edits/levels/event_stages.py
BCSFE_FIX/edits/levels/gauntlet.py
BCSFE_FIX/edits/levels/itf_timed_scores.py
BCSFE_FIX/edits/levels/legend_quest.py
BCSFE_FIX/edits/levels/main_story.py
BCSFE_FIX/edits/levels/outbreaks.py
BCSFE_FIX/edits/levels/story_level_id_selector.py
BCSFE_FIX/edits/levels/towers.py
BCSFE_FIX/edits/levels/treasures.py
BCSFE_FIX/edits/levels/uncanny.py
bcsfe_fix_en-2.7.2.6.dist-info/LICENSE
bcsfe_fix_en-2.7.2.6.dist-info/METADATA
bcsfe_fix_en-2.7.2.6.dist-info/WHEEL
bcsfe_fix_en-2.7.2.6.dist-info/top_level.txt
bcsfe_fix_en-2.7.2.6.dist-info/RECORD
